dsdbmanager/__init__.py
dsdbmanager/cli.py
dsdbmanager/configuring.py
dsdbmanager/constants.py
dsdbmanager/dbobject.py
dsdbmanager/exceptions_.py
dsdbmanager/mssql_.py
dsdbmanager/mysql_.py
dsdbmanager/oracle_.py
dsdbmanager/snowflake_.py
dsdbmanager/teradata_.py
dsdbmanager/utils.py
test/__init__.py
test/test_configurer.py
test/test_connectors.py
test/test_dbobject.py
test/test_utils.py
dsdbmanager-1.0.6.dist-info/LICENSE
dsdbmanager-1.0.6.dist-info/METADATA
dsdbmanager-1.0.6.dist-info/WHEEL
dsdbmanager-1.0.6.dist-info/entry_points.txt
dsdbmanager-1.0.6.dist-info/top_level.txt
dsdbmanager-1.0.6.dist-info/RECORD
