Metadata-Version: 2.1
Name: dsdbmanager
Version: 1.0.6
Summary: Manage your data science databases
Home-page: https://github.com/jojoduquartier/dsdbmanager
Author: jojoduquartier
Author-email: 
License: UNKNOWN
Project-URL: Bug Reports, https://github.com/jojoduquartier/dsdbmanager/issues
Project-URL: Source, https://github.com/jojoduquartier/dsdbmanager/
Keywords: sqlalchemy data-science database-connections pandas
Platform: UNKNOWN
Classifier: Development Status :: 3 - Alpha
Classifier: Intended Audience :: Developers
Classifier: Topic :: Database :: Database Engines/Servers
Classifier: License :: OSI Approved :: MIT License
Classifier: Programming Language :: Python :: 3.6
Classifier: Programming Language :: Python :: 3.7
Requires-Python: >=3.6, <4
Requires-Dist: sqlalchemy
Requires-Dist: numpy (>=1.16.5)
Requires-Dist: pandas
Requires-Dist: toolz
Requires-Dist: click
Requires-Dist: cryptography
